setup.py
micropython_redis_cloudclient.egg-info/PKG-INFO
micropython_redis_cloudclient.egg-info/SOURCES.txt
micropython_redis_cloudclient.egg-info/dependency_links.txt
micropython_redis_cloudclient.egg-info/requires.txt
micropython_redis_cloudclient.egg-info/top_level.txt
micropython_redis_cloudclient.egg-info/zip-safe
redis_cloudclient/__init__.py
redis_cloudclient/console.py
redis_cloudclient/eventloop.py
redis_cloudclient/exceptions.py
redis_cloudclient/service.py