Metadata-Version: 1.0
Name: micropython-redis-cloudclient
Version: 0.0.56
Summary: Micropython client that allows network attached boards to be controlled from a central redis server
Home-page: https://github.com/dhubbard/micropython-redis-cloudclient
Author: Dwight Hubbard
Author-email: dwight@dwighthubbard.com
License: MIT
Platform: UNKNOWN
